fock_state_circuit/__init__.py
fock_state_circuit/circuit.py
fock_state_circuit/collection_of_states.py
fock_state_circuit/compound_circuit.py
fock_state_circuit/state.py
fock_state_circuit/nodes/bridge_nodes.py
fock_state_circuit/nodes/classical_nodes.py
fock_state_circuit/nodes/controlled_nodes.py
fock_state_circuit/nodes/custom_nodes.py
fock_state_circuit/nodes/measurement_nodes.py
fock_state_circuit/nodes/optical_nodes.py
fock_state_circuit/nodes/quantum_operator_nodes.py
fock_state_circuit/nodes/spectral_nodes.py
fock_state_circuit/nodes/superquantum_nodes.py
fock_state_circuit/nodes/nodelist/node_list.py
fock_state_circuit/nodes/nodelist/optical_values_component_names.py
fock_state_circuit/popescu_rohrlich_correlation_functionality/popescu_rohrlich_correlations.py
fock_state_circuit/popescu_rohrlich_correlation_functionality/popescu_rohrlich_photon_pair_amplitude_functionality.py
fock_state_circuit/quantum_operator_functionality/quantum_operators.py
fock_state_circuit/temporal_and_spectral_gate_functionality/collection_of_state_columns.py
fock_state_circuit/temporal_and_spectral_gate_functionality/column_of_states.py
fock_state_circuit/temporal_and_spectral_gate_functionality/interference_group.py
fock_state_circuit/temporal_and_spectral_gate_functionality/temporal_functions.py
fock_state_circuit/visualization/draw.py
fock_state_circuit/visualization/plot.py
FockStateCircuit-1.0.5.dist-info/LICENSE.txt
FockStateCircuit-1.0.5.dist-info/METADATA
FockStateCircuit-1.0.5.dist-info/WHEEL
FockStateCircuit-1.0.5.dist-info/top_level.txt
FockStateCircuit-1.0.5.dist-info/RECORD
