Metadata-Version: 2.1
Name: FockStateCircuit
Version: 1.0.5
Summary: Modelling quantum optical circuits
Author: Rob Hendriks
License: MIT License
Project-URL: Homepage, https://github.com/robhendrik/FockStateCircuit
Project-URL: Documentation, https://github.com/robhendrik/FockStateCircuit/tree/main
Project-URL: Repository, https://github.com/robhendrik/FockStateCircuit
Keywords: quantum,photon,optics,physics
Classifier: Programming Language :: Python
Requires-Python: >=3.12
License-File: LICENSE.txt
Requires-Dist: numpy >=1.26.4
Requires-Dist: matplotlib >=3.8.4
